anterval/__init__.py
anterval/core.py
anterval-0.1.0.dist-info/licenses/LICENSE
anterval-0.1.0.dist-info/METADATA
anterval-0.1.0.dist-info/WHEEL
anterval-0.1.0.dist-info/top_level.txt
anterval-0.1.0.dist-info/RECORD
