Metadata-Version: 2.4
Name: anterval
Version: 0.1.0
Summary: Abstract interval class.
Requires-Python: >=3.12
License-File: LICENSE
Dynamic: license-file
